hydra_client/__init__.py
hydra_client/cli.py
hydra_client/click.py
hydra_client/config.py
hydra_client/exception.py
hydra_client/objects.py
hydra_client/output.py
hydra_client/plugin.py
hydra_client/resources.py
hydra_client/templates.py
hydra_client/connection/__init__.py
hydra_client/connection/base_connection.py
hydra_client/connection/json_connection.py
hydra_client/connection/remote_json_connection.py
hydra_client_python-1.0.0.post0.dist-info/licenses/LICENSE.txt
hydra_client_python-1.0.0.post0.dist-info/METADATA
hydra_client_python-1.0.0.post0.dist-info/WHEEL
hydra_client_python-1.0.0.post0.dist-info/entry_points.txt
hydra_client_python-1.0.0.post0.dist-info/top_level.txt
hydra_client_python-1.0.0.post0.dist-info/RECORD
