Metadata-Version: 2.4
Name: hydra-client-python
Version: 1.0.0.post0
Summary: Client library to communicate with hydra platform
Author-email: Stephen Knox <knoxsp@gmail.com>
Project-URL: Documentation, https://hydraplatform.org
Project-URL: Repository, https://github.com/hydraplatform/hydra-client-python
Requires-Python: >=3.10
License-File: LICENSE.txt
Requires-Dist: hydra-base
Requires-Dist: lxml
Requires-Dist: requests
Requires-Dist: cryptography
Dynamic: license-file
